{
  "schema_version": 3,
  "status": "RUNTIME_LOOP_PREFLIGHT_GREEN",
  "branch": "codex/scene-first-remove-main-gd",
  "base_sha": "5b5b11ef123962553ca34c2483f57a32e392f3f0",
  "production_runtime_loop_created": false,
  "double_run_path_created": false,
  "main_process_is_unique_frame_entry": true,
  "table_presentation_scheduler_cadence_only": true,
  "main_consumes_presentation_receipts": false,
  "main_owns_world_geometry": false,
  "world_geometry_owner": "WorldSessionState",
  "legacy_scheduler_only_immediate_request_count": 0,
  "root_only_blockers": [],
  "resolved_blockers": [
    "card_resolution_transition_sink",
    "table_presentation_sources_targets",
    "victory_presentation_receipts"
    ,"world_geometry_truth"
  ],
  "time_semantics": {
    "production_multiplier_values": [0, 1],
    "runtime_pacing_state_required": false,
    "blocked_wager_delta": "real",
    "blocked_visual_delta": "real",
    "blocked_presentation_delta": "real",
    "ordinary_pause_advances": false,
    "active_world_clock_advances_per_frame": 1
  },
  "ordered_steps": [
    "session_finished_gate",
    "synchronize_forced_decisions",
    "global_time_block_gate",
    "blocked_wager_real_tick",
    "blocked_visual_real_tick",
    "blocked_table_presentation_real_tick",
    "ordinary_pause_gate",
    "world_delta_boundary",
    "advance_world_effective_clock_once",
    "synchronize_world_session_game_time",
    "card_resolution_gate_and_transition_sink",
    "contract_tick",
    "card_cooldowns",
    "gdp_derivative_timers",
    "futures_timers",
    "weather_tick",
    "economic_boon_ageing",
    "monster_wager_tick",
    "ai_tick",
    "monster_motion",
    "military_tick",
    "monster_actions",
    "monster_durations",
    "visual_cue_ageing",
    "monster_revivals",
    "commodity_flow_and_early_return",
    "post_flow_session_finished_gate",
    "product_market_cycle",
    "victory_advance_and_typed_presentation",
    "post_victory_session_finished_gate",
    "frame_end_table_presentation_real_tick"
  ],
  "remaining_typed_world_port_debt": [
    "ai",
    "monster",
    "military",
    "weather",
    "economy_product_route",
    "victory"
  ],
  "validation": {
    "focused_presentation_tests_passed": true,
    "godot_mcp_bench_passed": true,
    "main_architecture_gate_passed": true,
    "main_budget_gate_passed": true,
    "ui_text_smoke_passed": true,
    "visual_snapshot_passed": true,
    "smoke_check_only_passed": true,
    "full_smoke_passed": false,
    "full_smoke_first_failure": "AI uses reusable military commands to guard cities, strike rivals, attack monsters, and record command metadata",
    "full_smoke_first_missing_access": "_capture_run_state",
    "full_smoke_hang_debt": "_auto_monster_color"
  },
  "recommended_next_boundary": "AUTHORITATIVE_RUNTIME_LOOP_CUTOVER"
}
